blal/__init__.py
blal/__main__.py
blal-1.0.1.dist-info/LICENSE
blal-1.0.1.dist-info/METADATA
blal-1.0.1.dist-info/WHEEL
blal-1.0.1.dist-info/entry_points.txt
blal-1.0.1.dist-info/top_level.txt
blal-1.0.1.dist-info/RECORD
