Metadata-Version: 2.1
Name: blal
Version: 1.0.1
Summary: BLAL converter for LoZ:BotW
Home-page: https://github.com/GingerAvalanche/blal
Author: Ginger
Author-email: chodness@gmail.com
License: UNKNOWN
Platform: UNKNOWN
Classifier: Programming Language :: Python :: 3.7
Classifier: License :: OSI Approved :: GNU General Public License v3 or later (GPLv3+)
Classifier: Operating System :: OS Independent
Classifier: Development Status :: 5 - Production/Stable
Requires-Python: >=3.7
